MANIFEST.in
requirements.txt
setup.cfg
setup.py
test-requirements.txt
django_condition_chain/__init__.py
django_condition_chain/admin.py
django_condition_chain/models.py
django_condition_chain/urls.py
django_condition_chain/wsgi.py
django_condition_chain.egg-info/PKG-INFO
django_condition_chain.egg-info/SOURCES.txt
django_condition_chain.egg-info/dependency_links.txt
django_condition_chain.egg-info/namespace_packages.txt
django_condition_chain.egg-info/not-zip-safe
django_condition_chain.egg-info/requires.txt
django_condition_chain.egg-info/top_level.txt
django_condition_chain/migrations/0001_initial.py
django_condition_chain/migrations/0002_auto_20150920_2236.py
django_condition_chain/migrations/__init__.py
django_condition_chain/south_migrations/0001_initial.py
django_condition_chain/south_migrations/0002_auto__add_field_condition_custom_kwargs.py
django_condition_chain/south_migrations/__init__.py