Metadata-Version: 1.1
Name: django-condition-chain
Version: 0.0.9
Summary: Django Condition Chain app
Home-page: UNKNOWN
Author: Ellis Percival
Author-email: ellis@0x07.co.uk
License: UNKNOWN
Platform: UNKNOWN
Classifier: Programming Language :: Python
